{
  "$schema": "https://mintlify.com/docs.json",
  "name": "94Talent Docs",
  "theme": "mint",
  "colors": {
    "primary": "#b241f5",
    "light": "#b241f5",
    "dark": "#E1C8FA"
  },
  "favicon": "/FAVIcon.svg",
  "navigation": {
    "tabs": [
      {
        "tab": "Legal",
        "groups": [
          {
            "group": "Policies",
            "pages": [
              "privacy-policy",
              "terms-of-use",
              "dpa"
            ]
          }
        ]
      }
    ]
  },
  "logo": {
    "light": "/logo/new-logo-dark.svg",
    "dark": "/logo/new-logo-light.svg"
  },
  "navbar": {
    "links": []
  },
  "footer": {
    "socials": {}
  }
}
